openai_helper/__init__.py
openai_helper/bp/__init__.py
openai_helper/bp/openai_chat_completion.py
openai_helper/bp/openai_custom_model.py
openai_helper/bp/openai_text_completion.py
openai_helper/dmo/__init__.py
openai_helper/dmo/chat_message_formatter.py
openai_helper/dmo/completion_event_extractor.py
openai_helper/dmo/etl_handle_textcompletions.py
openai_helper/dmo/etl_remove_emojis.py
openai_helper/dmo/etl_remove_listindicators.py
openai_helper/dmo/etl_remove_promptindicators.py
openai_helper/dmo/etl_replace_cliches.py
openai_helper/dmo/etl_replace_duplicatedinput.py
openai_helper/dmo/input_token_counter.py
openai_helper/dmo/no_openai_event.py
openai_helper/dmo/openai_connector.py
openai_helper/dmo/output_extractor_chat.py
openai_helper/dmo/output_extractor_text.py
openai_helper/svc/__init__.py
openai_helper/svc/create_openai_answer.py
openai_helper/svc/extract_primary_topic.py
openai_helper/svc/extract_top_response.py
openai_helper/svc/run_chat_completion.py
openai_helper/svc/run_text_completion.py
openai_helper-0.2.4.dist-info/METADATA
openai_helper-0.2.4.dist-info/WHEEL
openai_helper-0.2.4.dist-info/RECORD
