Metadata-Version: 2.1
Name: openai-helper
Version: 0.2.4
Summary: OpenAI Helper for Easy I/O
Home-page: https://github.com/craigtrim/openai-helper
License: MIT
Keywords: openai,api,utility
Author: Craig Trim
Author-email: craigtrim@gmail.com
Maintainer: Craig Trim
Maintainer-email: craigtrim@gmail.com
Requires-Python: >=3.8.5,<4.0.0
Classifier: Development Status :: 4 - Beta
Classifier: License :: OSI Approved :: MIT License
Classifier: Programming Language :: Python :: 3
Classifier: Programming Language :: Python :: 3.9
Classifier: Programming Language :: Python :: 3.10
Classifier: Programming Language :: Python :: 3.11
Classifier: Topic :: Scientific/Engineering :: Artificial Intelligence
Classifier: Topic :: Software Development :: Libraries :: Python Modules
Requires-Dist: baseblock
Requires-Dist: openai (>=0.27.8,<0.28.0)
Requires-Dist: tiktoken
Project-URL: Bug Tracker, https://github.com/craigtrim/openai-helper/issues
Project-URL: Repository, https://github.com/craigtrim/openai-helper
